rasa_denerator/__init__.py
rasa_denerator/__main__.py
rasa_denerator/rasa_denerator.py
rasa_denerator-1.0.4.dist-info/LICENSE
rasa_denerator-1.0.4.dist-info/METADATA
rasa_denerator-1.0.4.dist-info/WHEEL
rasa_denerator-1.0.4.dist-info/entry_points.txt
rasa_denerator-1.0.4.dist-info/top_level.txt
rasa_denerator-1.0.4.dist-info/RECORD
