Metadata-Version: 2.1
Name: rasa-denerator
Version: 1.0.4
Summary: A simple way of generating a domain.yml file for Rasa
Home-page: https://github.com/Collen-Roller/Rasa-Denerator
Author: Collen Roller
Author-email: collen.roller@gmail.com
License: UNKNOWN
Keywords: rasa,rasa_core,rasa_nlu
Platform: UNKNOWN
Classifier: Programming Language :: Python :: 2.7
Classifier: Programming Language :: Python :: 3
Classifier: Programming Language :: Python :: 3.5
Classifier: Programming Language :: Python :: 3.6
Classifier: Programming Language :: Python :: 3.7
Classifier: License :: OSI Approved :: MIT License
Classifier: Operating System :: OS Independent
Requires-Dist: rasa (~=1.3)
Requires-Dist: typing (==3.6.2)
Requires-Dist: rasa-sdk (~=1.3)
Requires-Dist: ruamel.base (==1.0.0)
